django_userservice-3.2.2.dist-info/licenses/LICENSE
userservice/VERSION
userservice/__init__.py
userservice/decorators.py
userservice/logging.py
userservice/models.py
userservice/urls.py
userservice/user.py
userservice/username.py
userservice/validation.py
userservice/views.py
userservice/templates/no_access.html
userservice/templates/support.html
userservice/templates/support_wrapper.html
userservice/test/__init__.py
userservice/test/test_api.py
userservice/test/test_middleware.py
userservice/test/test_username.py
userservice/test/test_view.py
django_userservice-3.2.2.dist-info/METADATA
django_userservice-3.2.2.dist-info/WHEEL
django_userservice-3.2.2.dist-info/top_level.txt
django_userservice-3.2.2.dist-info/RECORD
