Metadata-Version: 2.4
Name: Django-UserService
Version: 3.2.2
Summary: User abstraction and impersonation for Django
Home-page: https://github.com/uw-it-aca/django-userservice
Author: UW-IT Student & Educational Technology Services
Author-email: aca-it@uw.edu
License: Apache License, Version 2.0
Classifier: Intended Audience :: Developers
Classifier: License :: OSI Approved :: Apache Software License
Classifier: Operating System :: OS Independent
Classifier: Programming Language :: Python
License-File: LICENSE
Requires-Dist: django<6,>=3.2
Dynamic: author
Dynamic: author-email
Dynamic: classifier
Dynamic: description
Dynamic: home-page
Dynamic: license
Dynamic: license-file
Dynamic: requires-dist
Dynamic: summary
